typro/__init__.py
typro/__main__.py
typro/cli.py
typro/key_test.py
typro/data/cmd
typro/data/default
typro/data/fortune
typro/data/pycomp
typro/data/pyplot
typro/data/pyroot
typro/data/root
typro/data/www.google.com
typro-0.2.5.dist-info/LICENSE
typro-0.2.5.dist-info/METADATA
typro-0.2.5.dist-info/WHEEL
typro-0.2.5.dist-info/entry_points.txt
typro-0.2.5.dist-info/top_level.txt
typro-0.2.5.dist-info/RECORD
