Metadata-Version: 2.1
Name: typro
Version: 0.2.5
Summary: typing game on console
Home-page: https://github.com/mzks/typro
Author: Keita Mizukoshi
Author-email: mzks@stu.kobe-u.ac.jp
Maintainer: Keita Mizukoshi
Maintainer-email: mzks@stu.kobe-u.ac.jp
License: MIT
Classifier: Programming Language :: Python :: 3
Classifier: License :: OSI Approved :: MIT License
License-File: LICENSE
Requires-Dist: numpy
Requires-Dist: pandas
Requires-Dist: requests
